wide_wild_west/__init__.py
wide_wild_west/data.py
wide_wild_west/main.py
WorkshopIL_Nallar-0.0.1.dev2.dist-info/LICENSE.txt
WorkshopIL_Nallar-0.0.1.dev2.dist-info/METADATA
WorkshopIL_Nallar-0.0.1.dev2.dist-info/WHEEL
WorkshopIL_Nallar-0.0.1.dev2.dist-info/top_level.txt
WorkshopIL_Nallar-0.0.1.dev2.dist-info/RECORD
