Metadata-Version: 2.1
Name: WorkshopIL-Nallar
Version: 0.0.1.dev2
Summary: A sample project.
Home-page: https://bitbucket.org/tncy/my-project2/
Author: Thomas LC
Author-email: thomas.le-corre@telecomnnancy.net
License: Apache License, Version 2.0
Platform: UNKNOWN
Classifier: Programming Language :: Python
Classifier: Development Status :: 1 - Planning
Classifier: Operating System :: OS Independent
Classifier: Programming Language :: Python :: 3.7
Classifier: Intended Audience :: Education
Requires-Dist: monkey.ioc (>=0.0.1.dev3)
